kivy_garden/draggable/__init__.py
kivy_garden/draggable/_impl.py
kivy_garden/draggable/_utils.py
kivy_garden_draggable-0.3.0.dist-info/METADATA
kivy_garden_draggable-0.3.0.dist-info/WHEEL
kivy_garden_draggable-0.3.0.dist-info/RECORD
