Metadata-Version: 2.3
Name: kivy-garden-draggable
Version: 0.3.0
Summary: Drag & Drop Extension for Kivy
License: MIT
Keywords: kivy
Author: Nattōsai Mitō
Author-email: flow4re2c@gmail.com
Requires-Python: >=3.10,<4.0
Classifier: Development Status :: 5 - Production/Stable
Classifier: Intended Audience :: Developers
Classifier: License :: OSI Approved :: MIT License
Classifier: Operating System :: OS Independent
Classifier: Programming Language :: Python
Classifier: Programming Language :: Python :: 3
Classifier: Programming Language :: Python :: 3.10
Classifier: Programming Language :: Python :: 3.11
Classifier: Programming Language :: Python :: 3.12
Classifier: Programming Language :: Python :: 3.13
Classifier: Topic :: Software Development :: Libraries
Requires-Dist: asynckivy (>=0.9,<0.10)
Project-URL: Homepage, https://github.com/kivy-garden/draggable
Project-URL: Repository, https://github.com/kivy-garden/draggable
